safevision_face/__init__.py
safevision_face/config.py
safevision_face/database.py
safevision_face/detection.py
safevision_face/extraction.py
safevision_face/utils.py
safevision_face/feature_extraction/__init__.py
safevision_face/feature_extraction/edgeface_extractor.py
safevision_face/feature_extraction/feature_extractor.py
safevision_face/feature_extraction/models/__init__.py
safevision_face/feature_extraction/models/edgeface_s_gamma_05.onnx
safevision_face/model/__init__.py
safevision_face/model/yolov11m-face.pt
safeai_face-0.0.3.1.dist-info/METADATA
safeai_face-0.0.3.1.dist-info/WHEEL
safeai_face-0.0.3.1.dist-info/top_level.txt
safeai_face-0.0.3.1.dist-info/RECORD
